gh_utils/__init__.py
gh_utils/config.py
gh_utils/gh_create_repo_and_add_to_remote.py
gh_utils/parse.py
gh_utils/switch_between_https_and_ssh_remote_types.py
gh_utils/types.py
gh_utils/utils.py
gh_utils-0.6.9.dist-info/LICENSE
gh_utils-0.6.9.dist-info/METADATA
gh_utils-0.6.9.dist-info/WHEEL
gh_utils-0.6.9.dist-info/entry_points.txt
gh_utils-0.6.9.dist-info/RECORD
