Metadata-Version: 2.1
Name: gh-utils
Version: 0.6.9
Summary: GitHub CLI Utilities
Home-page: https://github.com/tddschn/gh-utils
License: MIT
Keywords: gh,github,utils
Author: Xinyuan Chen
Author-email: 45612704+tddschn@users.noreply.github.com
Requires-Python: >=3.10,<4.0
Classifier: License :: OSI Approved :: MIT License
Classifier: Programming Language :: Python :: 3
Classifier: Programming Language :: Python :: 3.10
Classifier: Programming Language :: Python :: 3.11
Classifier: Programming Language :: Python :: 3.12
Classifier: Topic :: Utilities
Requires-Dist: PyYAML (>=6.0.1,<7.0.0)
Project-URL: Bug Tracker, https://github.com/tddschn/gh-utils/issues
Project-URL: Repository, https://github.com/tddschn/gh-utils
